MANIFEST.in
README.md
setup.py
klar/__init__.py
klar/importers.py
klar/klar.py
klar.egg-info/PKG-INFO
klar.egg-info/SOURCES.txt
klar.egg-info/dependency_links.txt
klar.egg-info/requires.txt
klar.egg-info/top_level.txt