Metadata-Version: 1.1
Name: klar
Version: 0.0.5
Summary: a micro web framework
Home-page: https://github.com/zweifisch/klar
Author: Feng Zhou
Author-email: zf.pascal@gmail.com
License: MIT
Keywords: micro web framework restful
Platform: UNKNOWN
Classifier: Development Status :: 3 - Alpha
Classifier: Environment :: Web Environment
Classifier: Operating System :: OS Independent
Classifier: Intended Audience :: Developers
Classifier: License :: OSI Approved :: MIT License
Classifier: Programming Language :: Python :: 3.3
Classifier: Topic :: Internet :: WWW/HTTP :: WSGI
